[{"id":7533101,"ast":1,"blk":0,"dreb":3,"fg3_pct":37.5,"fg3a":8,"fg3m":3,"fg_pct":45.5,"fga":11,"fgm":5,"ft_pct":0,"fta":0,"ftm":0,"game":{"id":473464,"date":"2021-10-27T00:00:00.000Z","home_team_id":17,"home_team_score":108,"period":4,"postseason":false,"season":2021,"status":"Final","time":"","visitor_team_id":18,"visitor_team_score":113},"min":"29:54","oreb":1,"pf":3,"player":{"id":8,"first_name":"Grayson","height_feet":6,"height_inches":5,"last_name":"Allen","position":"G","team_id":17,"weight_pounds":198},"pts":13,"reb":4,"stl":1,"team":{"id":17,"abbreviation":"MIL","city":"Milwaukee","conference":"East","division":"Central","full_name":"Milwaukee Bucks","name":"Bucks"},"turnover":0},{"id":7913794,"ast":3,"blk":0,"dreb":2,"fg3_pct":55.6,"fg3a":9,"fg3m":5,"fg_pct":61.5,"fga":13,"fgm":8,"ft_pct":100,"fta":4,"ftm":4,"game":{"id":473563,"date":"2021-11-09T00:00:00.000Z","home_team_id":23,"home_team_score":109,"period":4,"postseason":false,"season":2021,"status":"Final","time":"","visitor_team_id":17,"visitor_team_score":118},"min":"32:50","oreb":0,"pf":1,"player":{"id":8,"first_name":"Grayson","height_feet":6,"height_inches":5,"last_name":"Allen","position":"G","team_id":17,"weight_pounds":198},"pts":25,"reb":2,"stl":0,"team":{"id":17,"abbreviation":"MIL","city":"Milwaukee","conference":"East","division":"Central","full_name":"Milwaukee Bucks","name":"Bucks"},"turnover":0},{"id":7980045,"ast":0,"blk":0,"dreb":3,"fg3_pct":55.6,"fg3a":9,"fg3m":5,"fg_pct":37.5,"fga":16,"fgm":6,"ft_pct":80,"fta":5,"ftm":4,"game":{"id":473584,"date":"2021-11-12T00:00:00.000Z","home_team_id":2,"home_team_score":122,"period":5,"postseason":false,"season":2021,"status":"Final","time":"","visitor_team_id":17,"visitor_team_score":113},"min":"34:35","oreb":1,"pf":4,"player":{"id":8,"first_name":"Grayson","height_feet":6,"height_inches":5,"last_name":"Allen","position":"G","team_id":17,"weight_pounds":198},"pts":21,"reb":4,"stl":1,"team":{"id":17,"abbreviation":"MIL","city":"Milwaukee","conference":"East","division":"Central","full_name":"Milwaukee Bucks","name":"Bucks"},"turnover":1},{"id":8122160,"ast":1,"blk":0,"dreb":7,"fg3_pct":20,"fg3a":5,"fg3m":1,"fg_pct":33.3,"fga":6,"fgm":2,"ft_pct":0,"fta":0,"ftm":0,"game":{"id":473627,"date":"2021-11-17T00:00:00.000Z","home_team_id":17,"home_team_score":109,"period":4,"postseason":false,"season":2021,"status":"Final","time":"","visitor_team_id":14,"visitor_team_score":84},"min":"30:40","oreb":1,"pf":1,"player":{"id":8,"first_name":"Grayson","height_feet":6,"height_inches":5,"last_name":"Allen","position":"G","team_id":17,"weight_pounds":198},"pts":5,"reb":8,"stl":0,"team":{"id":17,"abbreviation":"MIL","city":"Milwaukee","conference":"East","division":"Central","full_name":"Milwaukee Bucks","name":"Bucks"},"turnover":0},{"id":12292641,"ast":1,"blk":1,"dreb":3,"fg3_pct":0.5,"fg3a":6,"fg3m":3,"fg_pct":0.625,"fga":8,"fgm":5,"ft_pct":0,"fta":0,"ftm":0,"game":{"id":473369,"date":"2021-10-05T00:00:00.000Z","home_team_id":15,"home_team_score":87,"period":4,"postseason":false,"season":2021,"status":"Final","time":"Final","visitor_team_id":17,"visitor_team_score":77},"min":"17","oreb":0,"pf":0,"player":{"id":8,"first_name":"Grayson","height_feet":6,"height_inches":5,"last_name":"Allen","position":"G","team_id":17,"weight_pounds":198},"pts":13,"reb":3,"stl":0,"team":{"id":17,"abbreviation":"MIL","city":"Milwaukee","conference":"East","division":"Central","full_name":"Milwaukee Bucks","name":"Bucks"},"turnover":0},{"id":8317156,"ast":2,"blk":0,"dreb":3,"fg3_pct":25,"fg3a":4,"fg3m":1,"fg_pct":16.7,"fga":6,"fgm":1,"ft_pct":0,"fta":0,"ftm":0,"game":{"id":473678,"date":"2021-11-24T00:00:00.000Z","home_team_id":17,"home_team_score":114,"period":4,"postseason":false,"season":2021,"status":"Final","time":"","visitor_team_id":9,"visitor_team_score":93},"min":"24:16","oreb":0,"pf":1,"player":{"id":8,"first_name":"Grayson","height_feet":6,"height_inches":5,"last_name":"Allen","position":"G","team_id":17,"weight_pounds":198},"pts":3,"reb":3,"stl":0,"team":{"id":17,"abbreviation":"MIL","city":"Milwaukee","conference":"East","division":"Central","full_name":"Milwaukee Bucks","name":"Bucks"},"turnover":1},{"id":7798425,"ast":2,"blk":1,"dreb":4,"fg3_pct":66.7,"fg3a":9,"fg3m":6,"fg_pct":66.7,"fga":12,"fgm":8,"ft_pct":0,"fta":0,"ftm":0,"game":{"id":473532,"date":"2021-11-05T00:00:00.000Z","home_team_id":17,"home_team_score":98,"period":4,"postseason":false,"season":2021,"status":"Final","time":"","visitor_team_id":20,"visitor_team_score":113},"min":"31:10","oreb":1,"pf":2,"player":{"id":8,"first_name":"Grayson","height_feet":6,"height_inches":5,"last_name":"Allen","position":"G","team_id":17,"weight_pounds":198},"pts":22,"reb":5,"stl":1,"team":{"id":17,"abbreviation":"MIL","city":"Milwaukee","conference":"East","division":"Central","full_name":"Milwaukee Bucks","name":"Bucks"},"turnover":0},{"id":8926736,"ast":0,"blk":0,"dreb":0,"fg3_pct":0,"fg3a":0,"fg3m":0,"fg_pct":0,"fga":0,"fgm":0,"ft_pct":0,"fta":0,"ftm":0,"game":{"id":473849,"date":"2021-12-18T00:00:00.000Z","home_team_id":17,"home_team_score":90,"period":4,"postseason":false,"season":2021,"status":"Final","time":"","visitor_team_id":6,"visitor_team_score":119},"min":"0:00","oreb":0,"pf":0,"player":{"id":8,"first_name":"Grayson","height_feet":6,"height_inches":5,"last_name":"Allen","position":"G","team_id":17,"weight_pounds":198},"pts":0,"reb":0,"stl":0,"team":{"id":17,"abbreviation":"MIL","city":"Milwaukee","conference":"East","division":"Central","full_name":"Milwaukee Bucks","name":"Bucks"},"turnover":0},{"id":7367212,"ast":1,"blk":0,"dreb":3,"fg3_pct":25,"fg3a":8,"fg3m":2,"fg_pct":45.5,"fga":11,"fgm":5,"ft_pct":100,"fta":2,"ftm":2,"game":{"id":473423,"date":"2021-10-21T00:00:00.000Z","home_team_id":16,"home_team_score":137,"period":4,"postseason":false,"season":2021,"status":"Final","time":"","visitor_team_id":17,"visitor_team_score":95},"min":"28:38","oreb":0,"pf":2,"player":{"id":8,"first_name":"Grayson","height_feet":6,"height_inches":5,"last_name":"Allen","position":"G","team_id":17,"weight_pounds":198},"pts":14,"reb":3,"stl":0,"team":{"id":17,"abbreviation":"MIL","city":"Milwaukee","conference":"East","division":"Central","full_name":"Milwaukee Bucks","name":"Bucks"},"turnover":1},{"id":8433903,"ast":4,"blk":1,"dreb":2,"fg3_pct":50,"fg3a":4,"fg3m":2,"fg_pct":60,"fga":5,"fgm":3,"ft_pct":0,"fta":0,"ftm":0,"game":{"id":473711,"date":"2021-11-28T00:00:00.000Z","home_team_id":12,"home_team_score":100,"period":4,"postseason":false,"season":2021,"status":"Final","time":"","visitor_team_id":17,"visitor_team_score":118},"min":"30:08","oreb":0,"pf":1,"player":{"id":8,"first_name":"Grayson","height_feet":6,"height_inches":5,"last_name":"Allen","position":"G","team_id":17,"weight_pounds":198},"pts":8,"reb":2,"stl":1,"team":{"id":17,"abbreviation":"MIL","city":"Milwaukee","conference":"East","division":"Central","full_name":"Milwaukee Bucks","name":"Bucks"},"turnover":0},{"id":9695278,"ast":0,"blk":0,"dreb":2,"fg3_pct":20,"fg3a":5,"fg3m":1,"fg_pct":37.5,"fga":8,"fgm":3,"ft_pct":100,"fta":2,"ftm":2,"game":{"id":474082,"date":"2022-01-19T00:00:00.000Z","home_team_id":17,"home_team_score":126,"period":4,"postseason":false,"season":2021,"status":"Final","time":"","visitor_team_id":15,"visitor_team_score":114},"min":"25:50","oreb":1,"pf":1,"player":{"id":8,"first_name":"Grayson","height_feet":6,"height_inches":5,"last_name":"Allen","position":"G","team_id":17,"weight_pounds":198},"pts":9,"reb":3,"stl":1,"team":{"id":17,"abbreviation":"MIL","city":"Milwaukee","conference":"East","division":"Central","full_name":"Milwaukee Bucks","name":"Bucks"},"turnover":1},{"id":7420165,"ast":1,"blk":0,"dreb":5,"fg3_pct":25,"fg3a":8,"fg3m":2,"fg_pct":36.4,"fga":11,"fgm":4,"ft_pct":0,"fta":0,"ftm":0,"game":{"id":473442,"date":"2021-10-23T00:00:00.000Z","home_team_id":27,"home_team_score":111,"period":4,"postseason":false,"season":2021,"status":"Final","time":"","visitor_team_id":17,"visitor_team_score":121},"min":"26:01","oreb":0,"pf":0,"player":{"id":8,"first_name":"Grayson","height_feet":6,"height_inches":5,"last_name":"Allen","position":"G","team_id":17,"weight_pounds":198},"pts":10,"reb":5,"stl":1,"team":{"id":17,"abbreviation":"MIL","city":"Milwaukee","conference":"East","division":"Central","full_name":"Milwaukee Bucks","name":"Bucks"},"turnover":0},{"id":7475929,"ast":0,"blk":1,"dreb":4,"fg3_pct":44.4,"fg3a":9,"fg3m":4,"fg_pct":45.5,"fga":11,"fgm":5,"ft_pct":100,"fta":5,"ftm":5,"game":{"id":473452,"date":"2021-10-25T00:00:00.000Z","home_team_id":12,"home_team_score":109,"period":4,"postseason":false,"season":2021,"status":"Final","time":"","visitor_team_id":17,"visitor_team_score":119},"min":"31:44","oreb":0,"pf":3,"player":{"id":8,"first_name":"Grayson","height_feet":6,"height_inches":5,"last_name":"Allen","position":"G","team_id":17,"weight_pounds":198},"pts":19,"reb":4,"stl":1,"team":{"id":17,"abbreviation":"MIL","city":"Milwaukee","conference":"East","division":"Central","full_name":"Milwaukee Bucks","name":"Bucks"},"turnover":1},{"id":7662542,"ast":0,"blk":0,"dreb":4,"fg3_pct":50,"fg3a":10,"fg3m":5,"fg_pct":42.9,"fga":14,"fgm":6,"ft_pct":50,"fta":2,"ftm":1,"game":{"id":473499,"date":"2021-10-31T00:00:00.000Z","home_team_id":17,"home_team_score":95,"period":4,"postseason":false,"season":2021,"status":"Final","time":"","visitor_team_id":29,"visitor_team_score":107},"min":"31:16","oreb":2,"pf":5,"player":{"id":8,"first_name":"Grayson","height_feet":6,"height_inches":5,"last_name":"Allen","position":"G","team_id":17,"weight_pounds":198},"pts":18,"reb":6,"stl":0,"team":{"id":17,"abbreviation":"MIL","city":"Milwaukee","conference":"East","division":"Central","full_name":"Milwaukee Bucks","name":"Bucks"},"turnover":1},{"id":7853403,"ast":2,"blk":0,"dreb":1,"fg3_pct":37.5,"fg3a":8,"fg3m":3,"fg_pct":50,"fga":12,"fgm":6,"ft_pct":100,"fta":4,"ftm":4,"game":{"id":473549,"date":"2021-11-07T00:00:00.000Z","home_team_id":30,"home_team_score":101,"period":4,"postseason":false,"season":2021,"status":"Final","time":"","visitor_team_id":17,"visitor_team_score":94},"min":"34:05","oreb":0,"pf":0,"player":{"id":8,"first_name":"Grayson","height_feet":6,"height_inches":5,"last_name":"Allen","position":"G","team_id":17,"weight_pounds":198},"pts":19,"reb":1,"stl":4,"team":{"id":17,"abbreviation":"MIL","city":"Milwaukee","conference":"East","division":"Central","full_name":"Milwaukee Bucks","name":"Bucks"},"turnover":1},{"id":8214208,"ast":1,"blk":0,"dreb":5,"fg3_pct":36.4,"fg3a":11,"fg3m":4,"fg_pct":42.9,"fga":14,"fgm":6,"ft_pct":0,"fta":0,"ftm":0,"game":{"id":473651,"date":"2021-11-20T00:00:00.000Z","home_team_id":17,"home_team_score":117,"period":4,"postseason":false,"season":2021,"status":"Final","time":"","visitor_team_id":22,"visitor_team_score":108},"min":"28:44","oreb":2,"pf":0,"player":{"id":8,"first_name":"Grayson","height_feet":6,"height_inches":5,"last_name":"Allen","position":"G","team_id":17,"weight_pounds":198},"pts":16,"reb":7,"stl":0,"team":{"id":17,"abbreviation":"MIL","city":"Milwaukee","conference":"East","division":"Central","full_name":"Milwaukee Bucks","name":"Bucks"},"turnover":1},{"id":8266147,"ast":1,"blk":0,"dreb":2,"fg3_pct":66.7,"fg3a":3,"fg3m":2,"fg_pct":62.5,"fga":8,"fgm":5,"ft_pct":66.7,"fta":3,"ftm":2,"game":{"id":473666,"date":"2021-11-22T00:00:00.000Z","home_team_id":17,"home_team_score":123,"period":4,"postseason":false,"season":2021,"status":"Final","time":"","visitor_team_id":22,"visitor_team_score":92},"min":"18:41","oreb":0,"pf":1,"player":{"id":8,"first_name":"Grayson","height_feet":6,"height_inches":5,"last_name":"Allen","position":"G","team_id":17,"weight_pounds":198},"pts":14,"reb":2,"stl":0,"team":{"id":17,"abbreviation":"MIL","city":"Milwaukee","conference":"East","division":"Central","full_name":"Milwaukee Bucks","name":"Bucks"},"turnover":1},{"id":8367181,"ast":0,"blk":0,"dreb":2,"fg3_pct":40,"fg3a":5,"fg3m":2,"fg_pct":50,"fga":6,"fgm":3,"ft_pct":100,"fta":2,"ftm":2,"game":{"id":473692,"date":"2021-11-26T00:00:00.000Z","home_team_id":8,"home_team_score":109,"period":4,"postseason":false,"season":2021,"status":"Final","time":"","visitor_team_id":17,"visitor_team_score":120},"min":"24:26","oreb":0,"pf":2,"player":{"id":8,"first_name":"Grayson","height_feet":6,"height_inches":5,"last_name":"Allen","position":"G","team_id":17,"weight_pounds":198},"pts":10,"reb":2,"stl":0,"team":{"id":17,"abbreviation":"MIL","city":"Milwaukee","conference":"East","division":"Central","full_name":"Milwaukee Bucks","name":"Bucks"},"turnover":0},{"id":8671187,"ast":1,"blk":0,"dreb":4,"fg3_pct":28.6,"fg3a":7,"fg3m":2,"fg_pct":33.3,"fga":9,"fgm":3,"ft_pct":0,"fta":0,"ftm":0,"game":{"id":473779,"date":"2021-12-08T00:00:00.000Z","home_team_id":16,"home_team_score":113,"period":4,"postseason":false,"season":2021,"status":"Final","time":"","visitor_team_id":17,"visitor_team_score":104},"min":"25:15","oreb":0,"pf":0,"player":{"id":8,"first_name":"Grayson","height_feet":6,"height_inches":5,"last_name":"Allen","position":"G","team_id":17,"weight_pounds":198},"pts":8,"reb":4,"stl":0,"team":{"id":17,"abbreviation":"MIL","city":"Milwaukee","conference":"East","division":"Central","full_name":"Milwaukee Bucks","name":"Bucks"},"turnover":0},{"id":8727477,"ast":0,"blk":0,"dreb":2,"fg3_pct":28.6,"fg3a":7,"fg3m":2,"fg_pct":37.5,"fga":8,"fgm":3,"ft_pct":0,"fta":1,"ftm":0,"game":{"id":473793,"date":"2021-12-10T00:00:00.000Z","home_team_id":11,"home_team_score":114,"period":4,"postseason":false,"season":2021,"status":"Final","time":"","visitor_team_id":17,"visitor_team_score":123},"min":"27:32","oreb":0,"pf":0,"player":{"id":8,"first_name":"Grayson","height_feet":6,"height_inches":5,"last_name":"Allen","position":"G","team_id":17,"weight_pounds":198},"pts":8,"reb":2,"stl":1,"team":{"id":17,"abbreviation":"MIL","city":"Milwaukee","conference":"East","division":"Central","full_name":"Milwaukee Bucks","name":"Bucks"},"turnover":2},{"id":8776789,"ast":2,"blk":0,"dreb":3,"fg3_pct":50,"fg3a":4,"fg3m":2,"fg_pct":55.6,"fga":9,"fgm":5,"ft_pct":0,"fta":0,"ftm":0,"game":{"id":473808,"date":"2021-12-12T00:00:00.000Z","home_team_id":20,"home_team_score":97,"period":4,"postseason":false,"season":2021,"status":"Final","time":"","visitor_team_id":17,"visitor_team_score":112},"min":"28:45","oreb":0,"pf":1,"player":{"id":8,"first_name":"Grayson","height_feet":6,"height_inches":5,"last_name":"Allen","position":"G","team_id":17,"weight_pounds":198},"pts":12,"reb":3,"stl":1,"team":{"id":17,"abbreviation":"MIL","city":"Milwaukee","conference":"East","division":"Central","full_name":"Milwaukee Bucks","name":"Bucks"},"turnover":1},{"id":9003260,"ast":0,"blk":0,"dreb":0,"fg3_pct":0,"fg3a":0,"fg3m":0,"fg_pct":0,"fga":0,"fgm":0,"ft_pct":0,"fta":0,"ftm":0,"game":{"id":473882,"date":"2021-12-22T00:00:00.000Z","home_team_id":17,"home_team_score":126,"period":4,"postseason":false,"season":2021,"status":"Final","time":"","visitor_team_id":11,"visitor_team_score":106},"min":"0:00","oreb":0,"pf":0,"player":{"id":8,"first_name":"Grayson","height_feet":6,"height_inches":5,"last_name":"Allen","position":"G","team_id":17,"weight_pounds":198},"pts":0,"reb":0,"stl":0,"team":{"id":17,"abbreviation":"MIL","city":"Milwaukee","conference":"East","division":"Central","full_name":"Milwaukee Bucks","name":"Bucks"},"turnover":0},{"id":9187107,"ast":0,"blk":0,"dreb":0,"fg3_pct":25,"fg3a":4,"fg3m":1,"fg_pct":20,"fga":5,"fgm":1,"ft_pct":50,"fta":2,"ftm":1,"game":{"id":473934,"date":"2021-12-30T00:00:00.000Z","home_team_id":22,"home_team_score":118,"period":4,"postseason":false,"season":2021,"status":"Final","time":"","visitor_team_id":17,"visitor_team_score":136},"min":"22:33","oreb":0,"pf":0,"player":{"id":8,"first_name":"Grayson","height_feet":6,"height_inches":5,"last_name":"Allen","position":"G","team_id":17,"weight_pounds":198},"pts":4,"reb":0,"stl":1,"team":{"id":17,"abbreviation":"MIL","city":"Milwaukee","conference":"East","division":"Central","full_name":"Milwaukee Bucks","name":"Bucks"},"turnover":0},{"id":11234726,"ast":1,"blk":0,"dreb":3,"fg3_pct":33.3,"fg3a":3,"fg3m":1,"fg_pct":50,"fga":6,"fgm":3,"ft_pct":0,"fta":0,"ftm":0,"game":{"id":474522,"date":"2022-03-26T00:00:00.000Z","home_team_id":15,"home_team_score":127,"period":4,"postseason":false,"season":2021,"status":"Final","time":"","visitor_team_id":17,"visitor_team_score":102},"min":"29:57","oreb":0,"pf":4,"player":{"id":8,"first_name":"Grayson","height_feet":6,"height_inches":5,"last_name":"Allen","position":"G","team_id":17,"weight_pounds":198},"pts":7,"reb":3,"stl":0,"team":{"id":17,"abbreviation":"MIL","city":"Milwaukee","conference":"East","division":"Central","full_name":"Milwaukee Bucks","name":"Bucks"},"turnover":2},{"id":7620440,"ast":1,"blk":0,"dreb":4,"fg3_pct":44.4,"fg3a":9,"fg3m":4,"fg_pct":36.4,"fga":11,"fgm":4,"ft_pct":0,"fta":0,"ftm":0,"game":{"id":473488,"date":"2021-10-30T00:00:00.000Z","home_team_id":17,"home_team_score":93,"period":4,"postseason":false,"season":2021,"status":"Final","time":"","visitor_team_id":27,"visitor_team_score":102},"min":"29:20","oreb":1,"pf":2,"player":{"id":8,"first_name":"Grayson","height_feet":6,"height_inches":5,"last_name":"Allen","position":"G","team_id":17,"weight_pounds":198},"pts":12,"reb":5,"stl":0,"team":{"id":17,"abbreviation":"MIL","city":"Milwaukee","conference":"East","division":"Central","full_name":"Milwaukee Bucks","name":"Bucks"},"turnover":1}]